Workbook

Sheet исходники
A1: Копия Конкурентный анализ амазон (Виталий) | B1: выгрузка конкурентного листинга с амазон

Sheet Inositol PPC
A1: Metric | B1: Метрика | C1: 1 | D1: 2 | E1: 3 | F1: 4 | G1: 5 | H1: 6 | I1: 7 | J1: 8 | K1: 9 | L1: 10 | M1: 11 | N1: 12
A2: Units Sold | B2: Ед. продано | C2: 50 | D2: 100 | E2: 200 | F2: 200 | G2: 300 | H2: 300 | I2: 400 | J2: 400 | K2: 500 | L2: 500 | M2: 600 | N2: 600
A3: ASP | B3: Ср. цена | C3: 16 | D3: 16 | E3: 16 | F3: 16 | G3: 16 | H3: 16 | I3: 17 | J3: 17 | K3: 17 | L3: 17 | M3: 17 | N3: 17
A4: COGS per unit | B4: Себестоимость | C4: =3.65+0.25 -> 3.9 | D4: =3.65+0.25 -> 3.9 | E4: =3.65+0.25 -> 3.9 | F4: =3.65+0.25 -> 3.9 | G4: =3.65+0.25 -> 3.9 | H4: =3.65+0.25 -> 3.9 | I4: =3.65+0.25 -> 3.9 | J4: =3.65+0.25 -> 3.9 | ... N4: =3.65+0.25 -> 3.9
A5: Inbound per unit | B5: Pan-European Amazon комиссия
A6: FBA fee per unit | B6: Фулфилмент | C6: 3.29 | D6: 3.29 | E6: 3.29 | F6: 3.29 | G6: 3.29 | H6: 3.29 | I6: 3.29 | J6: 3.29 | K6: 3.29 | L6: 3.29 | M6: 3.29 | N6: 3.29
A7: PPC % of Net Revenue | B7: ДДР | C7: 0.8 | D7: 0.7 | E7: 0.6 | F7: 0.6 | G7: 0.5 | H7: 0.4 | I7: 0.4 | J7: 0.3 | K7: 0.3 | L7: 0.3 | M7: 0.3 | N7: 0.3
A8: Return Rate | B8: Процент возвратов | C8: 0.01 | D8: 0.01 | E8: 0.01 | F8: 0.01 | G8: 0.01 | H8: 0.01 | I8: 0.01 | J8: 0.01 | K8: 0.01 | L8: 0.01 | M8: 0.01 | N8: 0.01
A9: Gross Revenue | B9: Гросс выручка | C9: =C2*C3 -> 800 | D9: =D2*D3 -> 1600 | E9: =E2*E3 -> 3200 | F9: =F2*F3 -> 3200 | G9: =G2*G3 -> 4800 | H9: =H2*H3 -> 4800 | I9: =I2*I3 -> 6800 | J9: =J2*J3 -> 6800 | ... N9: =N2*N3 -> 10200
A10: Return Units | B10: Возвращено ед. | C10: =C2*C8 -> 0.5 | D10: =D2*D8 -> 1 | E10: =E2*E8 -> 2 | F10: =F2*F8 -> 2 | G10: =G2*G8 -> 3 | H10: =H2*H8 -> 3 | I10: =I2*I8 -> 4 | J10: =J2*J8 -> 4 | ... N10: =N2*N8 -> 6
A11: Return Revenue Loss | B11: Списано на возвраты | C11: =C10*C3 -> 8 | D11: =D10*D3 -> 16 | E11: =E10*E3 -> 32 | F11: =F10*F3 -> 32 | G11: =G10*G3 -> 48 | H11: =H10*H3 -> 48 | I11: =I10*I3 -> 68 | J11: =J10*J3 -> 68 | ... N11: =N10*N3 -> 102
A12: Net Revenue | B12: Нетт выручка | C12: =C9-C11 -> 792 | D12: =D9-D11 -> 1584 | E12: =E9-E11 -> 3168 | F12: =F9-F11 -> 3168 | G12: =G9-G11 -> 4752 | H12: =H9-H11 -> 4752 | I12: =I9-I11 -> 6732 | J12: =J9-J11 -> 6732 | ... N12: =N9-N11 -> 10098
A13: COGS total | B13: Себестоимость итого | C13: =C2*C4 -> 195 | D13: =D2*D4 -> 390 | E13: =E2*E4 -> 780 | F13: =F2*F4 -> 780 | G13: =G2*G4 -> 1170 | H13: =H2*H4 -> 1170 | I13: =I2*I4 -> 1560 | J13: =J2*J4 -> 1560 | ... N13: =N2*N4 -> 2340
A14: Inbound total | B14: Pan-European Amazon итого | C14: =C9*C5 -> 0 | D14: =D9*D5 -> 0 | E14: =E9*E5 -> 0 | F14: =F9*F5 -> 0 | G14: =G9*G5 -> 0 | H14: =H9*H5 -> 0 | I14: =I9*I5 -> 0 | J14: =J9*J5 -> 0 | ... N14: =N9*N5 -> 0
A15: FBA total | B15: Фулфилмент итого | C15: =C2*C6 -> 164.5 | D15: =D2*D6 -> 329 | E15: =E2*E6 -> 658 | F15: =F2*F6 -> 658 | G15: =G2*G6 -> 987 | H15: =H2*H6 -> 987 | I15: =I2*I6 -> 1316 | J15: =J2*J6 -> 1316 | ... N15: =N2*N6 -> 1974
A16: Storage total | B16: Хранение Амазон итого | C16: =C27*Inputs!$B$3 -> 500 | D16: =D27*Inputs!$B$3 -> 475 | E16: =E27*Inputs!$B$3 -> 425 | F16: =F27*Inputs!$B$3 -> 325 | G16: =G27*Inputs!$B$3 -> 225 | H16: =H27*Inputs!$B$3 -> 75 | I16: =I27*Inputs!$B$3 -> 425 | J16: =J27*Inputs!$B$3 -> 225 | ... N16: =N27*Inputs!$B$3 -> 225
A17: Refund loss total | B17: Итого за утилизацияю возвратов | C17: =C10*Inputs!$B$4 -> 0.5 | D17: =D10*Inputs!$B$4 -> 1 | E17: =E10*Inputs!$B$4 -> 2 | F17: =F10*Inputs!$B$4 -> 2 | G17: =G10*Inputs!$B$4 -> 3 | H17: =H10*Inputs!$B$4 -> 3 | I17: =I10*Inputs!$B$4 -> 4 | J17: =J10*Inputs!$B$4 -> 4 | ... N17: =N10*Inputs!$B$4 -> 6
A18: Referral fee | B18: Комиссия за продажу итого | C18: =Inputs!$B$2*C12 -> 118.8 | D18: =Inputs!$B$2*D12 -> 237.6 | E18: =Inputs!$B$2*E12 -> 475.2 | F18: =Inputs!$B$2*F12 -> 475.2 | G18: =Inputs!$B$2*G12 -> 712.8 | H18: =Inputs!$B$2*H12 -> 712.8 | I18: =Inputs!$B$2*I12 -> 1009.8 | J18: =Inputs!$B$2*J12 -> 1009.8 | ... N18: =Inputs!$B$2*N12 -> 1514.7
A19: Variable Costs total | B19: Итого переменные | C19: =SUM(C13:C18) -> 978.8 | D19: =SUM(D13:D18) -> 1432.6 | E19: =SUM(E13:E18) -> 2340.2 | F19: =SUM(F13:F18) -> 2240.2 | G19: =SUM(G13:G18) -> 3097.8 | H19: =SUM(H13:H18) -> 2947.8 | I19: =SUM(I13:I18) -> 4314.8 | J19: =SUM(J13:J18) -> 4114.8 | ... N19: =SUM(N13:N18) -> 6059.7
A20: Gross Profit | B20: Гросс прибыль | C20: =C12-C19 -> -186.8 | D20: =D12-D19 -> 151.4 | E20: =E12-E19 -> 827.8 | F20: =F12-F19 -> 927.8 | G20: =G12-G19 -> 1654.2 | H20: =H12-H19 -> 1804.2 | I20: =I12-I19 -> 2417.2 | J20: =J12-J19 -> 2617.2 | ... N20: =N12-N19 -> 4038.3
A21: PPC spend | B21: Расходы на продвижение итого | C21: =C7*C12 -> 633.6 | D21: =D7*D12 -> 1108.8 | E21: =E7*E12 -> 1900.8 | F21: =F7*F12 -> 1900.8 | G21: =G7*G12 -> 2376 | H21: =H7*H12 -> 1900.8 | I21: =I7*I12 -> 2692.8 | J21: =J7*J12 -> 2019.6 | ... N21: =N7*N12 -> 3029.4
A22: Coupons cost | B22: Стомость купонов (скидки) итого | C22: =Inputs!$B$5*C12 -> 55.44 | D22: =Inputs!$B$5*D12 -> 110.88 | E22: =Inputs!$B$5*E12 -> 221.76 | F22: =Inputs!$B$5*F12 -> 221.76 | G22: =Inputs!$B$5*G12 -> 332.64 | H22: =Inputs!$B$5*H12 -> 332.64 | I22: =Inputs!$B$5*I12 -> 471.24 | J22: =Inputs!$B$5*J12 -> 471.24 | ... N22: =Inputs!$B$5*N12 -> 706.86
A23: Deals cost | B23: Стоимость участия в акциях итого | I23: =Inputs!$B$6*I12 -> 471.24 | J23: =Inputs!$B$6*J12 -> 471.24 | K23: =Inputs!$B$6*K12 -> 589.05 | L23: =Inputs!$B$6*L12 -> 589.05 | M23: =Inputs!$B$6*M12 -> 706.86 | N23: =Inputs!$B$6*N12 -> 706.86
A24: Operating costs | B24: Операционные расходы итого | C24: =SUM(C21:C23) -> 689.04 | D24: =SUM(D21:D23) -> 1219.68 | E24: =SUM(E21:E23) -> 2122.56 | F24: =SUM(F21:F23) -> 2122.56 | G24: =SUM(G21:G23) -> 2708.64 | H24: =SUM(H21:H23) -> 2233.44 | I24: =SUM(I21:I23) -> 3635.28 | J24: =SUM(J21:J23) -> 2962.08 | ... N24: =SUM(N21:N23) -> 4443.12
A25: Operating Profit | B25: Операционная прибыль итого | C25: =C20-C24 -> -875.84 | D25: =D20-D24 -> -1068.28 | E25: =E20-E24 -> -1294.76 | F25: =F20-F24 -> -1194.76 | G25: =G20-G24 -> -1054.44 | H25: =H20-H24 -> -429.24 | I25: =I20-I24 -> -1218.08 | J25: =J20-J24 -> -344.88 | ... N25: =N20-N24 -> -404.82
A26: Margin | B26: Маржинальность | C26: =C25/C9 -> -1.0948 | D26: =D25/D9 -> -0.667675 | E26: =E25/E9 -> -0.4046125 | F26: =F25/F9 -> -0.3733625 | G26: =G25/G9 -> -0.219675 | H26: =H25/H9 -> -0.089425 | I26: =I25/I9 -> -0.17912941 | J26: =J25/J9 -> -0.050717647 | ... N26: =N25/N9 -> -0.039688235
A27: Stock | B27: Сток ед. | C27: 1000 | D27: =C27-C2 -> 950 | E27: =D27-D2 -> 850 | F27: =E27-E2 -> 650 | G27: =F27-F2 -> 450 | H27: =G27-G2 -> 150 | I27: =1000+H27-H2 -> 850 | J27: =I27-I2 -> 450 | K27: =2000+J27-J2 -> 2050 | L27: =K27-K2 -> 1550 | M27: =L27-L2 -> 1050 | N27: =M27-M2 -> 450

Sheet Magnesium PPC
A1: Metric | B1: Метрика | C1: 1 | D1: 2 | E1: 3 | F1: 4 | G1: 5 | H1: 6 | I1: 7 | J1: 8 | K1: 9 | L1: 10 | M1: 11 | N1: 12
A2: Units Sold | B2: Ед. продано | C2: 100 | D2: 200 | E2: 300 | F2: 400 | G2: 400 | H2: 500 | I2: 500 | J2: 600 | K2: 600 | L2: 700 | M2: 800 | N2: 900
A3: ASP | B3: Ср. цена | C3: 18 | D3: 18 | E3: 18 | F3: 19 | G3: 19 | H3: 19 | I3: 20 | J3: 20 | K3: 20 | L3: 21 | M3: 21 | N3: 21
A4: COGS per unit | B4: Себестоимость | C4: =5.84+0.25 -> 6.09 | D4: =5.84+0.25 -> 6.09 | E4: =5.84+0.25 -> 6.09 | F4: =5.84+0.25 -> 6.09 | G4: =5.84+0.25 -> 6.09 | H4: =5.84+0.25 -> 6.09 | I4: =5.84+0.25 -> 6.09 | J4: =5.84+0.25 -> 6.09 | ... N4: =5.84+0.25 -> 6.09
A5: Inbound per unit | B5: Pan-European Amazon комиссия | C5: 0.2 | D5: 0.2 | E5: 0.2 | F5: 0.2 | G5: 0.2 | H5: 0.2 | I5: 0.2 | J5: 0.2 | K5: 0.2 | L5: 0.2 | M5: 0.2 | N5: 0.2
A6: FBA fee per unit | B6: Фулфилмент | C6: 4.13 | D6: 4.13 | E6: 4.13 | F6: 4.13 | G6: 4.13 | H6: 4.13 | I6: 4.13 | J6: 4.13 | K6: 4.13 | L6: 4.13 | M6: 4.13 | N6: 4.13
A7: PPC % of Net Revenue | B7: ДДР | C7: 0.8 | D7: 0.7 | E7: 0.6 | F7: 0.6 | G7: 0.5 | H7: 0.4 | I7: 0.4 | J7: 0.3 | K7: 0.3 | L7: 0.3 | M7: 0.3 | N7: 0.3
A8: Return Rate | B8: Процент возвратов | C8: 0.01 | D8: 0.01 | E8: 0.01 | F8: 0.01 | G8: 0.01 | H8: 0.01 | I8: 0.01 | J8: 0.01 | K8: 0.01 | L8: 0.01 | M8: 0.01 | N8: 0.01
A9: Gross Revenue | B9: Гросс выручка | C9: =C2*C3 -> 1800 | D9: =D2*D3 -> 3600 | E9: =E2*E3 -> 5400 | F9: =F2*F3 -> 7600 | G9: =G2*G3 -> 7600 | H9: =H2*H3 -> 9500 | I9: =I2*I3 -> 10000 | J9: =J2*J3 -> 12000 | ... N9: =N2*N3 -> 18900
A10: Return Units | B10: Возвращено ед. | C10: =C2*C8 -> 1 | D10: =D2*D8 -> 2 | E10: =E2*E8 -> 3 | F10: =F2*F8 -> 4 | G10: =G2*G8 -> 4 | H10: =H2*H8 -> 5 | I10: =I2*I8 -> 5 | J10: =J2*J8 -> 6 | ... N10: =N2*N8 -> 9
A11: Return Revenue Loss | B11: Списано на возвраты | C11: =C10*C3 -> 18 | D11: =D10*D3 -> 36 | E11: =E10*E3 -> 54 | F11: =F10*F3 -> 76 | G11: =G10*G3 -> 76 | H11: =H10*H3 -> 95 | I11: =I10*I3 -> 100 | J11: =J10*J3 -> 120 | ... N11: =N10*N3 -> 189
A12: Net Revenue | B12: Нетт выручка | C12: =C9-C11 -> 1782 | D12: =D9-D11 -> 3564 | E12: =E9-E11 -> 5346 | F12: =F9-F11 -> 7524 | G12: =G9-G11 -> 7524 | H12: =H9-H11 -> 9405 | I12: =I9-I11 -> 9900 | J12: =J9-J11 -> 11880 | ... N12: =N9-N11 -> 18711
A13: COGS total | B13: Себестоимость итого | C13: =C2*C4 -> 609 | D13: =D2*D4 -> 1218 | E13: =E2*E4 -> 1827 | F13: =F2*F4 -> 2436 | G13: =G2*G4 -> 2436 | H13: =H2*H4 -> 3045 | I13: =I2*I4 -> 3045 | J13: =J2*J4 -> 3654 | ... N13: =N2*N4 -> 5481
A14: Inbound total | B14: Pan-European Amazon итого | C14: =C2*C5 -> 20 | D14: =D2*D5 -> 40 | E14: =E2*E5 -> 60 | F14: =F2*F5 -> 80 | G14: =G2*G5 -> 80 | H14: =H2*H5 -> 100 | I14: =I2*I5 -> 100 | J14: =J2*J5 -> 120 | ... N14: =N2*N5 -> 180
A15: FBA total | B15: Фулфилмент итого | C15: =C2*C6 -> 413 | D15: =D2*D6 -> 826 | E15: =E2*E6 -> 1239 | F15: =F2*F6 -> 1652 | G15: =G2*G6 -> 1652 | H15: =H2*H6 -> 2065 | I15: =I2*I6 -> 2065 | J15: =J2*J6 -> 2478 | ... N15: =N2*N6 -> 3717
A16: Storage total | B16: Хранение Амазон итого | C16: =C27*Inputs!$B$3 -> 1000 | D16: =D27*Inputs!$B$3 -> 950 | E16: =E27*Inputs!$B$3 -> 850 | F16: =F27*Inputs!$B$3 -> 700 | G16: =G27*Inputs!$B$3 -> 500 | H16: =H27*Inputs!$B$3 -> 1300 | I16: =I27*Inputs!$B$3 -> 1050 | J16: =J27*Inputs!$B$3 -> 800 | ... N16: =N27*Inputs!$B$3 -> 450
A17: Refund loss total | B17: Итого за утилизацияю возвратов | C17: =C10*Inputs!$B$4 -> 1 | D17: =D10*Inputs!$B$4 -> 2 | E17: =E10*Inputs!$B$4 -> 3 | F17: =F10*Inputs!$B$4 -> 4 | G17: =G10*Inputs!$B$4 -> 4 | H17: =H10*Inputs!$B$4 -> 5 | I17: =I10*Inputs!$B$4 -> 5 | J17: =J10*Inputs!$B$4 -> 6 | ... N17: =N10*Inputs!$B$4 -> 9
A18: Referral fee | B18: Комиссия за продажу итого | C18: =Inputs!$B$2*C12 -> 267.3 | D18: =Inputs!$B$2*D12 -> 534.6 | E18: =Inputs!$B$2*E12 -> 801.9 | F18: =Inputs!$B$2*F12 -> 1128.6 | G18: =Inputs!$B$2*G12 -> 1128.6 | H18: =Inputs!$B$2*H12 -> 1410.75 | I18: =Inputs!$B$2*I12 -> 1485 | J18: =Inputs!$B$2*J12 -> 1782 | ... N18: =Inputs!$B$2*N12 -> 2806.65
A19: Variable Costs total | B19: Итого переменные | C19: =SUM(C13:C18) -> 2310.3 | D19: =SUM(D13:D18) -> 3570.6 | E19: =SUM(E13:E18) -> 4780.9 | F19: =SUM(F13:F18) -> 6000.6 | G19: =SUM(G13:G18) -> 5800.6 | H19: =SUM(H13:H18) -> 7925.75 | I19: =SUM(I13:I18) -> 7750 | J19: =SUM(J13:J18) -> 8840 | ... N19: =SUM(N13:N18) -> 12643.65
A20: Gross Profit | B20: Гросс прибыль | C20: =C12-C19 -> -528.3 | D20: =D12-D19 -> -6.6 | E20: =E12-E19 -> 565.1 | F20: =F12-F19 -> 1523.4 | G20: =G12-G19 -> 1723.4 | H20: =H12-H19 -> 1479.25 | I20: =I12-I19 -> 2150 | J20: =J12-J19 -> 3040 | ... N20: =N12-N19 -> 6067.35
A21: PPC spend | B21: Расходы на продвижение итого | C21: =C7*C12 -> 1425.6 | D21: =D7*D12 -> 2494.8 | E21: =E7*E12 -> 3207.6 | F21: =F7*F12 -> 4514.4 | G21: =G7*G12 -> 3762 | H21: =H7*H12 -> 3762 | I21: =I7*I12 -> 3960 | J21: =J7*J12 -> 3564 | ... N21: =N7*N12 -> 5613.3
A22: Coupons cost | B22: Стомость купонов (скидки) итого | C22: =Inputs!$B$5*C12 -> 124.74 | D22: =Inputs!$B$5*D12 -> 249.48 | E22: =Inputs!$B$5*E12 -> 374.22 | F22: =Inputs!$B$5*F12 -> 526.68 | G22: =Inputs!$B$5*G12 -> 526.68 | H22: =Inputs!$B$5*H12 -> 658.35 | I22: =Inputs!$B$5*I12 -> 693 | J22: =Inputs!$B$5*J12 -> 831.6 | ... N22: =Inputs!$B$5*N12 -> 1309.77
A23: Deals cost | B23: Стоимость участия в акциях итого | C23: =Inputs!$B$6*C12 -> 124.74 | D23: =Inputs!$B$6*D12 -> 249.48 | E23: =Inputs!$B$6*E12 -> 374.22 | F23: =Inputs!$B$6*F12 -> 526.68 | G23: =Inputs!$B$6*G12 -> 526.68 | H23: =Inputs!$B$6*H12 -> 658.35 | I23: =Inputs!$B$6*I12 -> 693 | J23: =Inputs!$B$6*J12 -> 831.6 | ... N23: =Inputs!$B$6*N12 -> 1309.77
A24: Operating costs | B24: Операционные расходы итого | C24: =SUM(C21:C23) -> 1675.08 | D24: =SUM(D21:D23) -> 2993.76 | E24: =SUM(E21:E23) -> 3956.04 | F24: =SUM(F21:F23) -> 5567.76 | G24: =SUM(G21:G23) -> 4815.36 | H24: =SUM(H21:H23) -> 5078.7 | I24: =SUM(I21:I23) -> 5346 | J24: =SUM(J21:J23) -> 5227.2 | ... N24: =SUM(N21:N23) -> 8232.84
A25: Operating Profit | B25: Операционная прибыль итого | C25: =C20-C24 -> -2203.38 | D25: =D20-D24 -> -3000.36 | E25: =E20-E24 -> -3390.94 | F25: =F20-F24 -> -4044.36 | G25: =G20-G24 -> -3091.96 | H25: =H20-H24 -> -3599.45 | I25: =I20-I24 -> -3196 | J25: =J20-J24 -> -2187.2 | ... N25: =N20-N24 -> -2165.49
A26: Margin | B26: Маржинальность | C26: =C25/C9 -> -1.2241 | D26: =D25/D9 -> -0.83343333 | E26: =E25/E9 -> -0.62795185 | F26: =F25/F9 -> -0.53215263 | G26: =G25/G9 -> -0.40683684 | H26: =H25/H9 -> -0.37888947 | I26: =I25/I9 -> -0.3196 | J26: =J25/J9 -> -0.18226667 | ... N26: =N25/N9 -> -0.11457619
A27: Stock | B27: Сток ед. | C27: 2000 | D27: =C27-C2 -> 1900 | E27: =D27-D2 -> 1700 | F27: =E27-E2 -> 1400 | G27: =F27-F2 -> 1000 | H27: =G27-G2+2000 -> 2600 | I27: =H27-H2 -> 2100 | J27: =I27-I2 -> 1600 | K27: =J27-J2 -> 1000 | L27: =K27-K2+2000 -> 2400 | M27: =L27-L2 -> 1700 | N27: =M27-M2 -> 900

Sheet Summary
A1: Metric | B1: Inositol | C1: Magnesium | D1: Probiotic qeep | E1: Retinol | F1: Probiotic Harly | G1: TOTAL
A2: Units Sold (year) | B2: =sum('Inositol PPC'!C2:N2) -> 4150 | C2: =sum('Magnesium PPC'!C2:N2) -> 6000 | G2: =SUM(B2:D2) -> 10150
A3: Net Revenue (year) | B3: =sum('Inositol PPC'!C12:N12) -> 68706 | C3: =sum('Magnesium PPC'!C12:N12) -> 118701 | G3: =SUM(B3:D3) -> 187407
A4: PPC spend (year) | B4: =sum('Inositol PPC'!C21:N21) -> 25641 | C4: =sum('Magnesium PPC'!C21:N21) -> 45223.2 | G4: =SUM(B4:D4) -> 70864.2
A5: Operating Profit (year) | B5: =sum('Inositol PPC'!C25:N25) -> -10689.62 | C5: =sum('Magnesium PPC'!C25:N25) -> -33675.49 | G5: =SUM(B5:D5) -> -44365.11
A6: Net Margin % | B6: =IFERROR(B5/B3,"") -> -0.15558496 | C6: =IFERROR(C5/C3,"") -> -0.28370014 | D6: =IFERROR(D5/D3,"") | G6: =IFERROR(G5/G3,"") -> -0.23673134
A7: Salaries (annual) | B7: =Inputs!$B$7*12 -> 18000 | C7: =Inputs!$B$7*12 -> 18000 | G7: =Inputs!$B$7*12 -> 18000
A8: Other OPEX (annual) | B8: =Inputs!$B$8*12 -> 6000 | C8: =Inputs!$B$8*12 -> 6000 | G8: =Inputs!$B$8*12 -> 6000
A9: Net Profit | B9: =B5-B7-B8 -> -34689.62 | C9: =C5-C7-C8 -> -57675.49 | G9: =G5-G7-G8 -> -68365.11
A10: TACoS (PPC/Net Rev) | B10: =IFERROR(B4/B3,"") -> 0.37319885 | C10: =IFERROR(C4/C3,"") -> 0.38098415 | D10: =IFERROR(D4/D3,"") | G10: =IFERROR(G4/G3,"") -> 0.37812995

Sheet Inputs
A1: Parameter | B1: Value
A2: Referral fee % of Net Revenue | B2: 0.15
A3: Storage fee per unit (period) | B3: 0.5
A4: Refund loss per returned unit | B4: 1
A5: Coupon % of Net Revenue | B5: 0.07
A6: Deals % of Net Revenue | B6: 0.07
A7: Salaries (fixed monthly) | B7: 1500
A8: Other OPEX (fixed monthly) | B8: 500
